ci/rtd-requirements.txt
ci/test-requirements.txt
ci/travis.sh
debian/.gitignore
debian/changelog
debian/control
debian/rules
debian/watch
debian/source/format
docs/Makefile
docs/make.bat
docs/source/conf.py
docs/source/history.rst
docs/source/index.rst
docs/source/usage.rst
docs/source/_static/.gitkeep
examples/line_echo.py
examples/line_echo_polled.py
examples/line_value.py
examples/push_button_event.py
moat/gpio/__init__.py
moat/gpio/gpio.py
moat/gpio/libgpiod.py
moat/gpio/test.py
moat_gpio-0.6.7.dist-info/licenses/LICENSE.APACHE2
moat_gpio-0.6.7.dist-info/licenses/LICENSE.MIT
moat_gpio-0.6.7.dist-info/licenses/LICENSE.txt
newsfragments/.gitkeep
newsfragments/README.rst
moat_gpio-0.6.7.dist-info/METADATA
moat_gpio-0.6.7.dist-info/WHEEL
moat_gpio-0.6.7.dist-info/top_level.txt
moat_gpio-0.6.7.dist-info/RECORD
